<template>

<t t-name="Booking">
    <div class="oe_booking_view">

        <!-- what a pity... OpenERP force the use of table layout if you want to be able to use % width and overflow hidden... -->
        <table class="oe-booking-container">
            <tr class="booking-chart">
                <td>
                    <div class="booking-calendar"></div>
                    <div class="booking-graph"></div>
                </td>
            </tr>
        </table>
        
    </div>
</t>

</template>
